odoo/addons/sale_margin_security/README.rst
odoo/addons/sale_margin_security/__init__.py
odoo/addons/sale_margin_security/__manifest__.py
odoo/addons/sale_margin_security/i18n/es_PA.po
odoo/addons/sale_margin_security/i18n/it.po
odoo/addons/sale_margin_security/i18n/pt.po
odoo/addons/sale_margin_security/i18n/pt_BR.po
odoo/addons/sale_margin_security/i18n/sale_margin_security.pot
odoo/addons/sale_margin_security/models/__init__.py
odoo/addons/sale_margin_security/models/sale_order.py
odoo/addons/sale_margin_security/readme/CONFIGURE.rst
odoo/addons/sale_margin_security/readme/CONTRIBUTORS.rst
odoo/addons/sale_margin_security/readme/DESCRIPTION.rst
odoo/addons/sale_margin_security/readme/USAGE.rst
odoo/addons/sale_margin_security/security/sale_margin_security_security.xml
odoo/addons/sale_margin_security/static/description/icon.png
odoo/addons/sale_margin_security/static/description/index.html
odoo/addons/sale_margin_security/views/sale_margin_security_view.xml
odoo12_addon_sale_margin_security-12.0.1.0.1.99.dev10.dist-info/METADATA
odoo12_addon_sale_margin_security-12.0.1.0.1.99.dev10.dist-info/WHEEL
odoo12_addon_sale_margin_security-12.0.1.0.1.99.dev10.dist-info/top_level.txt
odoo12_addon_sale_margin_security-12.0.1.0.1.99.dev10.dist-info/RECORD
